lshrs/__init__.py
lshrs/core/__init__.py
lshrs/core/config.py
lshrs/core/dataloader.py
lshrs/core/exceptions.py
lshrs/core/interfaces.py
lshrs/core/main.py
lshrs/encoding/__init__.py
lshrs/encoding/embedding.py
lshrs/encoding/main.py
lshrs/encoding/onehot.py
lshrs/encoding/tfidf.py
lshrs/hashing/__init__.py
lshrs/hashing/hyperplane.py
lshrs/hashing/lsh.py
lshrs/hashing/minhash.py
lshrs/preprocessing/__init__.py
lshrs/preprocessing/lemmatize.py
lshrs/preprocessing/shingling.py
lshrs/preprocessing/stopwords.py
lshrs/preprocessing/website.py
lshrs/utils/__init__.py
lshrs/utils/br.py
lshrs/utils/helpers.py
lshrs/utils/save.py
lshrs/utils/similarity.py
lshrs-0.1.0.dist-info/LICENSE
lshrs-0.1.0.dist-info/METADATA
lshrs-0.1.0.dist-info/WHEEL
lshrs-0.1.0.dist-info/RECORD
