Metadata-Version: 2.3
Name: lshrs
Version: 0.1.0
Summary: A Locality Sensitive Hashing based recommendation system for efficient similarity search.
License: MIT
Author: Y. Zhao
Author-email: yimingzhao936@gmail.com
Requires-Python: >3.11
Classifier: License :: OSI Approved :: MIT License
Classifier: Operating System :: OS Independent
Classifier: Programming Language :: Python :: 3
Classifier: Programming Language :: Python :: 3.12
Classifier: Programming Language :: Python :: 3.13
Requires-Dist: build
Requires-Dist: nltk
Requires-Dist: numpy
Requires-Dist: scikit-learn
Requires-Dist: scipy
Requires-Dist: twine
Project-URL: Homepage, https://github.com/mxngjxa/lshrs
Project-URL: Repository, https://github.com/mxngjxa/lshrs
